flask_cookie_decode/__init__.py
flask_cookie_decode/__main__.py
flask_cookie_decode/cookie_decode.py
flask_cookie_decode-0.4.3.dist-info/AUTHORS.rst
flask_cookie_decode-0.4.3.dist-info/LICENSE
flask_cookie_decode-0.4.3.dist-info/METADATA
flask_cookie_decode-0.4.3.dist-info/WHEEL
flask_cookie_decode-0.4.3.dist-info/entry_points.txt
flask_cookie_decode-0.4.3.dist-info/top_level.txt
flask_cookie_decode-0.4.3.dist-info/RECORD
