Metadata-Version: 2.2
Name: flask_cookie_decode
Version: 0.4.3
Summary: Tools for debugging and working with the built-in Flask session cookie
Home-page: https://github.com/wgwz/flask-cookie-decode
Author: Kyle Lawlor
Author-email: klawlor419@gmail.com
License: MIT license
Keywords: flask_cookie_decode
Classifier: Development Status :: 2 - Pre-Alpha
Classifier: Intended Audience :: Developers
Classifier: License :: OSI Approved :: MIT License
Classifier: Natural Language :: English
Classifier: Programming Language :: Python :: 2
Classifier: Programming Language :: Python :: 2.7
Classifier: Programming Language :: Python :: 3
Classifier: Programming Language :: Python :: 3.4
Classifier: Programming Language :: Python :: 3.5
Classifier: Programming Language :: Python :: 3.6
License-File: LICENSE
License-File: AUTHORS.rst
Requires-Dist: Flask>=0.11
Provides-Extra: test
Requires-Dist: pytest; extra == "test"
Requires-Dist: tox; extra == "test"
Requires-Dist: flake8; extra == "test"
Dynamic: author
Dynamic: author-email
Dynamic: classifier
Dynamic: description
Dynamic: description-content-type
Dynamic: home-page
Dynamic: keywords
Dynamic: license
Dynamic: provides-extra
Dynamic: requires-dist
Dynamic: summary
